cuda_hybrid/__init__.py
cuda_hybrid/model.py
cuda_hybrid-0.1.7.dist-info/METADATA
cuda_hybrid-0.1.7.dist-info/WHEEL
cuda_hybrid-0.1.7.dist-info/top_level.txt
cuda_hybrid-0.1.7.dist-info/RECORD
