Metadata-Version: 2.1
Name: cuda-hybrid
Version: 0.1.7
Summary: Run ABM/FCM models on CUDA cores
Home-page: https://github.com/cuda-hybrid/cuda-hybrid
License: UNKNOWN
Project-URL: Bug Tracker, https://github.com/cuda-hybrid/cuda-hybrid/issues
Project-URL: Documentation, https://cuda-hybrid.github.io/
Platform: UNKNOWN
Classifier: Programming Language :: Python :: 3
Classifier: License :: OSI Approved :: GNU General Public License v3 (GPLv3)
Classifier: Operating System :: OS Independent
Classifier: Environment :: GPU :: NVIDIA CUDA
Requires-Python: >=3.7, <4
Requires-Dist: setuptools (>=42)
Requires-Dist: networkx (>=2.6.3)
Requires-Dist: nptyping (>=1.4.4)
Requires-Dist: numba (>=0.48.0)
Requires-Dist: numpy (>=1.21.5)
